barcodecop/__init__.py
barcodecop/barcodecop.py
barcodecop/data/ver
barcodecop-0.4.1.dist-info/DESCRIPTION.rst
barcodecop-0.4.1.dist-info/METADATA
barcodecop-0.4.1.dist-info/RECORD
barcodecop-0.4.1.dist-info/WHEEL
barcodecop-0.4.1.dist-info/entry_points.txt
barcodecop-0.4.1.dist-info/metadata.json
barcodecop-0.4.1.dist-info/top_level.txt
tests/__init__.py
tests/test.py
