Metadata-Version: 2.0
Name: barcodecop
Version: 0.4.1
Summary: Enforce barcode match stringency and read quality in demultiplexed MiSeq reads
Home-page: https://github.com/nhoffman/barcodecop
Author: Noah Hoffman
Author-email: noah.hoffman@gmail.com
License: UNKNOWN
Platform: UNKNOWN
Classifier: Development Status :: 3 - Alpha
Classifier: Intended Audience :: Developers
Classifier: Operating System :: POSIX
Classifier: Programming Language :: Python :: 2.7
Classifier: Programming Language :: Python :: 3.3
Classifier: Programming Language :: Python :: 3.4
Classifier: Programming Language :: Python :: 3.5
Classifier: Programming Language :: Python :: 3.6
Requires-Dist: fastalite (==0.3)
